dockerlab/__init__.py
dockerlab/asset.py
dockerlab/assets/.gitignore
dockerlab/assets/Makefile
dockerlab/assets/docker-compose.yml
dockerlab/assets/docker.py
dockerlab/assets/misc/init_workspace
dockerlab/assets/requirements.txt
dockerlab/cli.py
dockerlab/post_templates/default.txt
dockerlab/post_templates/node.txt
dockerlab/post_templates/python.txt
dockerlab/template.py
dockerlab/templates/README.md
dockerlab/templates/runtime_node_lts/Dockerfile
dockerlab/templates/settting.py
dockerlab/templates/workspace_base/Dockerfile
dockerlab/templates/workspace_cuda_11_1/Dockerfile
dockerlab/templates/workspace_cuda_11_3/Dockerfile
dockerlab/templates/workspace_cuda_11_7/Dockerfile
dockerlab/templates/workspace_cuda_11_8/Dockerfile
dockerlab/templates/workspace_cuda_12_1/Dockerfile
dockerlab/templates/workspace_node_16/Dockerfile
dockerlab/templates/workspace_node_18/Dockerfile
dockerlab/templates/workspace_node_20/Dockerfile
dockerlab/templates/workspace_protein/Dockerfile
dockerlab/templates/workspace_pytorch_1_13/Dockerfile
dockerlab/templates/workspace_pytorch_2_0/Dockerfile
dockerlab/templates/workspace_pytorch_2_1/Dockerfile
dockerlab/templates/workspace_pytorch_2_2/Dockerfile
dockerlab/utils.py
dockerlab-0.3.29.dist-info/LICENSE
dockerlab-0.3.29.dist-info/METADATA
dockerlab-0.3.29.dist-info/WHEEL
dockerlab-0.3.29.dist-info/entry_points.txt
dockerlab-0.3.29.dist-info/RECORD
