Metadata-Version: 2.1
Name: dockerlab
Version: 0.3.29
Summary: Build a docker container as your workspace.
Home-page: https://github.com/hughplay/dockerlab
License: MIT
Author: Mr.Blue
Author-email: silverhugh.77@gmail.com
Requires-Python: >=3.8,<4.0
Classifier: License :: OSI Approved :: MIT License
Classifier: Programming Language :: Python :: 3
Classifier: Programming Language :: Python :: 3.8
Classifier: Programming Language :: Python :: 3.9
Classifier: Programming Language :: Python :: 3.10
Classifier: Programming Language :: Python :: 3.11
Classifier: Programming Language :: Python :: 3.12
Classifier: Programming Language :: Python :: 3.13
Requires-Dist: click (>=8.1.3,<9.0.0)
Requires-Dist: docker (>=5.0.0,<6.0.0)
Requires-Dist: toml (>=0.10.2,<0.11.0)
